{
  "name": "es-wikisource_es_all_novid",
  "lang": "es",
  "intended_use": "zim",
  "zim_name": "wikisource_es_all_novid",
  "title": "Wikisource en Español",
  "logo_url": "es-wikisource.png",
  "description": "Una biblioteca gratuita de textos de origen - los documentos que son enciclopedias hecha de - disponibles para su consulta. Este módulo es proporcionado por Kiwix.",
  "extra_html": "",
  "edit_status": "repo",
  "commit_sha": null,
  "previous_commit_sha": "7eef2258dd5c33e5c2c6880fad3441373e61d0d1",
  "change_ref": "copy from repo",
  "change_date": "2019-11-17"
}